pytest_nb_as_test/__init__.py
pytest_nb_as_test/item.py
pytest_nb_as_test/notebook_code.py
pytest_nb_as_test/options.py
pytest_nb_as_test/plugin.py
pytest_nb_as_test/timeout.py
pytest_nb_as_test-0.1.6.dist-info/licenses/LICENSE
pytest_nb_as_test-0.1.6.dist-info/METADATA
pytest_nb_as_test-0.1.6.dist-info/WHEEL
pytest_nb_as_test-0.1.6.dist-info/entry_points.txt
pytest_nb_as_test-0.1.6.dist-info/top_level.txt
pytest_nb_as_test-0.1.6.dist-info/RECORD
