Metadata-Version: 2.4
Name: pytest-nb-as-test
Version: 0.1.6
Summary: Use notebooks as pytests. Keep your notebooks working.
Author-email: Bryce Henson <pytest-nb-as-test+bryce.m.henson@gmail.com>
License-Expression: MIT
Project-URL: Homepage, https://github.com/brycehenson/pytest-nb-as-test
Requires-Python: <4.0,>=3.12
License-File: LICENSE
Requires-Dist: pytest<9.0.2,>=2.1.0
Requires-Dist: pytest-timeout>=2.0.0
Requires-Dist: nbformat
Provides-Extra: dev
Requires-Dist: ipykernel<8.0.0,>=7.0.1; extra == "dev"
Requires-Dist: ipywidgets==8.1.7; extra == "dev"
Requires-Dist: jupyterlab-widgets==3.0.15; extra == "dev"
Requires-Dist: black[jupyter]==25.9.0; extra == "dev"
Requires-Dist: isort==7.0.0; extra == "dev"
Requires-Dist: pylint==4.0.4; extra == "dev"
Requires-Dist: pytest-cov==4.1.0; extra == "dev"
Requires-Dist: pytest-asyncio<1.0.0,>=0.23.0; extra == "dev"
Requires-Dist: pytest-timeout<3.0.0,>=2.3.1; extra == "dev"
Requires-Dist: pytest-xdist<4.0.0,>=3.8.0; extra == "dev"
Requires-Dist: pyinstrument<6.0.0,>=5.1.1; extra == "dev"
Requires-Dist: nbformat<6.0.0,>=5.10.4; extra == "dev"
Requires-Dist: nbconvert<8.0.0,>=7.16.6; extra == "dev"
Requires-Dist: pyright==1.1.408; extra == "dev"
Requires-Dist: numpy; extra == "dev"
Requires-Dist: matplotlib; extra == "dev"
Requires-Dist: plotly; extra == "dev"
Dynamic: license-file
